{"stats":{"minecraft:used":{"minecraft:end_crystal":1,"minecraft:obsidian":1},"minecraft:mined":{"minecraft:large_fern":5,"minecraft:fern":1},"minecraft:picked_up":{"minecraft:bone":1,"minecraft:wheat_seeds":2,"minecraft:bedrock":64,"minecraft:spruce_log":1,"minecraft:cobblestone":16},"minecraft:killed":{"minecraft:skeleton":1},"minecraft:dropped":{"minecraft:wheat_seeds":2},"minecraft:custom":{"minecraft:time_since_rest":27252,"minecraft:crouch_one_cm":645,"minecraft:sprint_one_cm":1950,"minecraft:play_time":27252,"minecraft:damage_taken":228,"minecraft:walk_one_cm":7396,"minecraft:sneak_time":189,"minecraft:mob_kills":1,"minecraft:drop":2,"minecraft:jump":27,"minecraft:damage_dealt":176,"minecraft:leave_game":2,"minecraft:time_since_death":27252,"minecraft:total_world_time":27252,"minecraft:fly_one_cm":1961,"minecraft:fall_one_cm":2063}},"DataVersion":3465}